marianmt/__init__.py
mariannmt-0.0.1.dist-info/METADATA
mariannmt-0.0.1.dist-info/WHEEL
mariannmt-0.0.1.dist-info/top_level.txt
mariannmt-0.0.1.dist-info/RECORD
