Metadata-Version: 2.1
Name: mariannmt
Version: 0.0.1
Summary: mariannmt
Home-page: https://github.com/marian-nmt/marian-dev
Author: 
License: UNKNOWN
Platform: UNKNOWN
